{
    "category-v2.single.toJob": "pdi",
    "git.link": "https://github.com/echoedinvoker/pdi/blob/master/17-loading-into-mart/62-load-sales/memo.md",
    "course": "Pentaho for ETL & Data Integration Masterclass 2023 - PDI 9",
    "chapter": "17. Loading the data into a Data Mart",
    "section": "62. Loading sales data after database lookup steps",
    "video.length": 10,
    "time.comsuming": 81,
    "lecturer.name.first": "Start-Tech Academy",
    "register.time": "2023-02-11T13:12:25Z",
    "tag": [
      "etl","pdi","kettle","load","mart","output","table","fact","surrogate","replace","lookup"
    ],
    "video.link": "https://www.udemy.com/course/pentaho-for-etl-data-integration-masterclass/learn/lecture/21593940#content",
    "description": "Explain how to import data from PDI stream to database 'fact' table."
  }
